mdl_host_api/__init__.py
mdl_host_api/api.py
mdl_host_api/client.py
mdl_host_api/exceptions.py
mdl_host_api/task.py
mdl_host_api-0.0.5.dist-info/LICENSE
mdl_host_api-0.0.5.dist-info/METADATA
mdl_host_api-0.0.5.dist-info/WHEEL
mdl_host_api-0.0.5.dist-info/top_level.txt
mdl_host_api-0.0.5.dist-info/RECORD
